src/pwm.v

`default_nettype none
`timescale 1ns/1ns
module pwm (
    input wire clk, // drives the pwm signal
    input wire reset,
    output wire out,
    input wire [7:0] level
    );

	
	reg [7:0] counter; // keeps track of the clock cycle
	
	always @(posedge clk) begin
		if(reset) begin // if the reset signal is active
			counter <= 0;
	
		end else begin
			counter <= counter + 1'b1; // increments by 1 on each count cycle
		end
		
	end
	
	assign out = counter < level; // comparator -> 1 if true. 0 if false

endmodule

src/encoder.v
`default_nettype none
`timescale 1ns/1ns
module encoder (
    input clk,
    input reset,
    input a,
    input b,
    output reg [7:0] value
);

    reg old_a, old_b;

    always @(posedge clk) begin
        if(reset) begin
            old_a <= 0;
            old_b <= 0;
            value <= 0;
        end else begin
            old_a <= a;
            old_b <= b;


            case ({a, old_a, b, old_b})
                4'b1000: value <= value + 1;
                4'b0111: value <= value + 1;
                4'b0010: value <= value - 1;
                4'b1101: value <= value - 1;
            endcase 
        end
    end

endmodule

src/debounce.v
`default_nettype none
`timescale 1ns/1ns
module debounce (
    input wire clk,
    input wire reset,
    input wire button,
    output reg debounced
);

    reg [7:0] history;

    always @(posedge clk) begin
        if(reset) begin
            history <= 0;
        end else begin
            history <= {history[6:0], button}; // 7 bits + 1 button bit

            if (history == 8'b1111_1111)
                debounced <= 1;
            if (history == 8'b0000_0000)
                debounced <= 0;
        end

    end

endmodule

src/rgb_mixer.v
`default_nettype none
`timescale 1ns/1ns

module rgb_mixer (
    input clk,
    input reset,
    input enc0_a,
    input enc0_b,
    input enc1_a,
    input enc1_b,
    input enc2_a,
    input enc2_b,
    output pwm0_out,
    output pwm1_out,
    output pwm2_out
);

wire [7:0] enc0, enc1, enc2;
wire enc0_a_db, enc0_b_db;
wire enc1_a_db, enc1_b_db;
wire enc2_a_db, enc2_b_db;

// Instantiation for color channel 0
debounce debounce_0_a (.clk(clk), .reset(reset), .button(enc0_a), .debounced(enc0_a_db));
debounce debounce_0_b (.clk(clk), .reset(reset), .button(enc0_b), .debounced(enc0_b_db));
encoder encoder0 (.clk(clk), .reset(reset), .a(enc0_a_db), .b(enc0_b_db), .value(enc0));
pwm pwm0 (.clk(clk), .reset(reset), .out(pwm0_out), .level(enc0));

// Instantiation for color channel 1
debounce debounce_1_a (.clk(clk), .reset(reset), .button(enc1_a), .debounced(enc1_a_db));
debounce debounce_1_b (.clk(clk), .reset(reset), .button(enc1_b), .debounced(enc1_b_db));
encoder encoder1 (.clk(clk), .reset(reset), .a(enc1_a_db), .b(enc1_b_db), .value(enc1));
pwm pwm1 (.clk(clk), .reset(reset), .out(pwm1_out), .level(enc1));

// Instantiation for color channel 2
debounce debounce_2_a (.clk(clk), .reset(reset), .button(enc2_a), .debounced(enc2_a_db));
debounce debounce_2_b (.clk(clk), .reset(reset), .button(enc2_b), .debounced(enc2_b_db));
encoder encoder2 (.clk(clk), .reset(reset), .a(enc2_a_db), .b(enc2_b_db), .value(enc2));
pwm pwm2 (.clk(clk), .reset(reset), .out(pwm2_out), .level(enc2));

endmodule

rgb_mixer.vcd
$date
	Mon Apr  8 00:50:51 2024
$end
$version
	Icarus Verilog
$end
$timescale
	1ns
$end
$scope module rgb_mixer $end
$var wire 1 ! clk $end
$var wire 1 " enc0_a $end
$var wire 1 # enc0_b $end
$var wire 1 $ enc1_a $end
$var wire 1 % enc1_b $end
$var wire 1 & enc2_a $end
$var wire 1 ' enc2_b $end
$var wire 1 ( reset $end
$var wire 1 ) pwm2_out $end
$var wire 1 * pwm1_out $end
$var wire 1 + pwm0_out $end
$var wire 1 , enc2_b_db $end
$var wire 1 - enc2_a_db $end
$var wire 8 . enc2 [7:0] $end
$var wire 1 / enc1_b_db $end
$var wire 1 0 enc1_a_db $end
$var wire 8 1 enc1 [7:0] $end
$var wire 1 2 enc0_b_db $end
$var wire 1 3 enc0_a_db $end
$var wire 8 4 enc0 [7:0] $end
$scope module debounce_0_a $end
$var wire 1 " button $end
$var wire 1 ! clk $end
$var wire 1 ( reset $end
$var reg 1 3 debounced $end
$var reg 8 5 history [7:0] $end
$upscope $end
$scope module debounce_0_b $end
$var wire 1 # button $end
$var wire 1 ! clk $end
$var wire 1 ( reset $end
$var reg 1 2 debounced $end
$var reg 8 6 history [7:0] $end
$upscope $end
$scope module debounce_1_a $end
$var wire 1 $ button $end
$var wire 1 ! clk $end
$var wire 1 ( reset $end
$var reg 1 0 debounced $end
$var reg 8 7 history [7:0] $end
$upscope $end
$scope module debounce_1_b $end
$var wire 1 % button $end
$var wire 1 ! clk $end
$var wire 1 ( reset $end
$var reg 1 / debounced $end
$var reg 8 8 history [7:0] $end
$upscope $end
$scope module debounce_2_a $end
$var wire 1 & button $end
$var wire 1 ! clk $end
$var wire 1 ( reset $end
$var reg 1 - debounced $end
$var reg 8 9 history [7:0] $end
$upscope $end
$scope module debounce_2_b $end
$var wire 1 ' button $end
$var wire 1 ! clk $end
$var wire 1 ( reset $end
$var reg 1 , debounced $end
$var reg 8 : history [7:0] $end
$upscope $end
$scope module encoder0 $end
$var wire 1 3 a $end
$var wire 1 2 b $end
$var wire 1 ! clk $end
$var wire 1 ( reset $end
$var reg 1 ; old_a $end
$var reg 1 < old_b $end
$var reg 8 = value [7:0] $end
$upscope $end
$scope module encoder1 $end
$var wire 1 0 a $end
$var wire 1 / b $end
$var wire 1 ! clk $end
$var wire 1 ( reset $end
$var reg 1 > old_a $end
$var reg 1 ? old_b $end
$var reg 8 @ value [7:0] $end
$upscope $end
$scope module encoder2 $end
$var wire 1 - a $end
$var wire 1 , b $end
$var wire 1 ! clk $end
$var wire 1 ( reset $end
$var reg 1 A old_a $end
$var reg 1 B old_b $end
$var reg 8 C value [7:0] $end
$upscope $end
$scope module pwm0 $end
$var wire 1 ! clk $end
$var wire 8 D level [7:0] $end
$var wire 1 ( reset $end
$var wire 1 + out $end
$var reg 8 E counter [7:0] $end
$upscope $end
$scope module pwm1 $end
$var wire 1 ! clk $end
$var wire 8 F level [7:0] $end
$var wire 1 ( reset $end
$var wire 1 * out $end
$var reg 8 G counter [7:0] $end
$upscope $end
$scope module pwm2 $end
$var wire 1 ! clk $end
$var wire 8 H level [7:0] $end
$var wire 1 ( reset $end
$var wire 1 ) out $end
$var reg 8 I counter [7:0] $end
$upscope $end
$upscope $end
$enddefinitions $end
$comment Show the parameter values. $end
$dumpall
$end
#0
$dumpvars
b0 I
b0 H
b0 G
b0 F
b0 E
b0 D
b0 C
0B
0A
b0 @
0?
0>
b0 =
0<
0;
b0 :
b0 9
b0 8
b0 7
b0 6
b0 5
b0 4
x3
x2
b0 1
x0
x/
b0 .
x-
x,
0+
0*
0)
1(
0'
0&
0%
0$
0#
0"
1!
$end
#5000
0!
#10000
1!
#15000
0!
#20000
1!
#25000
0!
#30000
1!
#35000
0!
#40000
0(
1!
#45000
0!
#50000
b1 I
xB
xA
0,
0-
b1 G
x?
x>
0/
00
b1 E
x<
x;
02
03
1!
#55000
0!
#60000
0<
0;
b10 E
0?
0>
b10 G
0B
0A
b10 I
1!
#65000
0!
#70000
b11 I
b11 G
b11 E
1!
#75000
0!
#80000
b100 E
b100 G
b100 I
1!
#85000
0!
#90000
b101 I
b101 G
b101 E
1!
#95000
0!
#100000
1"
b110 E
b110 G
b110 I
1!
#105000
0!
#110000
b111 I
b111 G
b111 E
b1 5
1!
#115000
0!
#120000
0"
b11 5
b1000 E
b1000 G
b1000 I
1!
#125000
0!
#130000
b1001 I
b1001 G
b1001 E
b110 5
1!
#135000
0!
#140000
b1100 5
b1010 E
b1010 G
b1010 I
1!
#145000
0!
#150000
b1011 I
b1011 G
b1011 E
b11000 5
1!
#155000
0!
#160000
b110000 5
b1100 E
b1100 G
b1100 I
1!
#165000
0!
#170000
b1101 I
b1101 G
b1101 E
b1100000 5
1!
#175000
0!
#180000
b11000000 5
b1110 E
b1110 G
b1110 I
1!
#185000
0!
#190000
1"
b1111 I
b1111 G
b1111 E
b10000000 5
1!
#195000
0!
#200000
0"
b1 5
b10000 E
b10000 G
b10000 I
1!
#205000
0!
#210000
1"
b10001 I
b10001 G
b10001 E
b10 5
1!
#215000
0!
#220000
b101 5
b10010 E
b10010 G
b10010 I
1!
#225000
0!
#230000
b10011 I
b10011 G
b10011 E
b1011 5
1!
#235000
0!
#240000
b10111 5
b10100 E
b10100 G
b10100 I
1!
#245000
0!
#250000
b10101 I
b10101 G
b10101 E
b101111 5
1!
#255000
0!
#260000
b1011111 5
b10110 E
b10110 G
b10110 I
1!
#265000
0!
#270000
b10111 I
b10111 G
b10111 E
b10111111 5
1!
#275000
0!
#280000
b1111111 5
b11000 E
b11000 G
b11000 I
1!
#285000
0!
#290000
1#
b11001 I
b11001 G
b11001 E
b11111111 5
1!
#295000
0!
#300000
13
b1 6
b11010 E
b11010 G
b11010 I
1!
#305000
0!
#310000
0#
b11011 I
b11011 G
b11011 E
b1 4
b1 =
b1 D
1;
b11 6
1!
#315000
0!
#320000
1#
b110 6
b11100 E
b11100 G
b11100 I
1!
#325000
0!
#330000
b11101 I
b11101 G
b11101 E
b1101 6
1!
#335000
0!
#340000
b11011 6
b11110 E
b11110 G
b11110 I
1!
#345000
0!
#350000
b11111 I
b11111 G
b11111 E
b110111 6
1!
#355000
0!
#360000
b1101111 6
b100000 E
b100000 G
b100000 I
1!
#365000
0!
#370000
b100001 I
b100001 G
b100001 E
b11011111 6
1!
#375000
0!
#380000
b10111111 6
b100010 E
b100010 G
b100010 I
1!
#385000
0!
#390000
0"
b100011 I
b100011 G
b100011 E
b1111111 6
1!
#395000
0!
#400000
b11111110 5
b11111111 6
b100100 E
b100100 G
b100100 I
1!
#405000
0!
#410000
b100101 I
b100101 G
b100101 E
12
b11111100 5
1!
#415000
0!
#420000
b11111000 5
1<
b100110 E
b100110 G
b100110 I
1!
#425000
0!
#430000
b100111 I
b100111 G
b100111 E
b11110000 5
1!
#435000
0!
#440000
b11100000 5
b101000 E
b101000 G
b101000 I
1!
#445000
0!
#450000
b101001 I
b101001 G
b101001 E
b11000000 5
1!
#455000
0!
#460000
b10000000 5
b101010 E
b101010 G
b101010 I
1!
#465000
0!
#470000
b101011 I
b101011 G
b101011 E
b0 5
1!
#475000
0!
#480000
03
b101100 E
b101100 G
b101100 I
1!
#485000
0!
#490000
0#
b101101 I
b101101 G
b101101 E
b10 4
b10 =
b10 D
0;
1!
#495000
0!
#500000
b11111110 6
b101110 E
b101110 G
b101110 I
1!
#505000
0!
#510000
b101111 I
b101111 G
b101111 E
b11111100 6
1!
#515000
0!
#520000
b11111000 6
b110000 E
b110000 G
b110000 I
1!
#525000
0!
#530000
b110001 I
b110001 G
b110001 E
b11110000 6
1!
#535000
0!
#540000
b11100000 6
b110010 E
b110010 G
b110010 I
1!
#545000
0!
#550000
b110011 I
b110011 G
b110011 E
b11000000 6
1!
#555000
0!
#560000
b10000000 6
b110100 E
b110100 G
b110100 I
1!
#565000
0!
#570000
b110101 I
b110101 G
b110101 E
b0 6
1!
#575000
0!
#580000
02
b110110 E
b110110 G
b110110 I
1!
#585000
0!
#590000
1"
b110111 I
b110111 G
b110111 E
0<
1!
#595000
0!
#600000
b1 5
b111000 E
b111000 G
b111000 I
1!
#605000
0!
#610000
b111001 I
b111001 G
b111001 E
b11 5
1!
#615000
0!
#620000
b111 5
b111010 E
b111010 G
b111010 I
1!
#625000
0!
#630000
b111011 I
b111011 G
b111011 E
b1111 5
1!
#635000
0!
#640000
b11111 5
b111100 E
b111100 G
b111100 I
1!
#645000
0!
#650000
b111101 I
b111101 G
b111101 E
b111111 5
1!
#655000
0!
#660000
b1111111 5
b111110 E
b111110 G
b111110 I
1!
#665000
0!
#670000
b111111 I
b111111 G
b111111 E
b11111111 5
1!
#675000
0!
#680000
13
b1000000 E
b1000000 G
b1000000 I
1!
#685000
0!
#690000
b1000001 I
b1000001 G
b1000001 E
b11 4
b11 =
b11 D
1;
1!
#695000
0!
#700000
1#
b1000010 E
b1000010 G
b1000010 I
1!
#705000
0!
#710000
b1000011 I
b1000011 G
b1000011 E
b1 6
1!
#715000
0!
#720000
b11 6
b1000100 E
b1000100 G
b1000100 I
1!
#725000
0!
#730000
b1000101 I
b1000101 G
b1000101 E
b111 6
1!
#735000
0!
#740000
b1111 6
b1000110 E
b1000110 G
b1000110 I
1!
#745000
0!
#750000
b1000111 I
b1000111 G
b1000111 E
b11111 6
1!
#755000
0!
#760000
b111111 6
b1001000 E
b1001000 G
b1001000 I
1!
#765000
0!
#770000
b1001001 I
b1001001 G
b1001001 E
b1111111 6
1!
#775000
0!
#780000
b11111111 6
b1001010 E
b1001010 G
b1001010 I
1!
#785000
0!
#790000
0"
b1001011 I
b1001011 G
b1001011 E
12
1!
#795000
0!
#800000
b11111110 5
1<
b1001100 E
b1001100 G
b1001100 I
1!
#805000
0!
#810000
b1001101 I
b1001101 G
b1001101 E
b11111100 5
1!
#815000
0!
#820000
b11111000 5
b1001110 E
b1001110 G
b1001110 I
1!
#825000
0!
#830000
b1001111 I
b1001111 G
b1001111 E
b11110000 5
1!
#835000
0!
#840000
b11100000 5
b1010000 E
b1010000 G
b1010000 I
1!
#845000
0!
#850000
b1010001 I
b1010001 G
b1010001 E
b11000000 5
1!
#855000
0!
#860000
b10000000 5
b1010010 E
b1010010 G
b1010010 I
1!
#865000
0!
#870000
b1010011 I
b1010011 G
b1010011 E
b0 5
1!
#875000
0!
#880000
03
b1010100 E
b1010100 G
b1010100 I
1!
#885000
0!
#890000
0#
b1010101 I
b1010101 G
b1010101 E
b100 4
b100 =
b100 D
0;
1!
#895000
0!
#900000
1#
b11111110 6
b1010110 E
b1010110 G
b1010110 I
1!
#905000
0!
#910000
0#
b1010111 I
b1010111 G
b1010111 E
b11111101 6
1!
#915000
0!
#920000
b11111010 6
b1011000 E
b1011000 G
b1011000 I
1!
#925000
0!
#930000
b1011001 I
b1011001 G
b1011001 E
b11110100 6
1!
#935000
0!
#940000
b11101000 6
b1011010 E
b1011010 G
b1011010 I
1!
#945000
0!
#950000
b1011011 I
b1011011 G
b1011011 E
b11010000 6
1!
#955000
0!
#960000
b10100000 6
b1011100 E
b1011100 G
b1011100 I
1!
#965000
0!
#970000
b1011101 I
b1011101 G
b1011101 E
b1000000 6
1!
#975000
0!
#980000
b10000000 6
b1011110 E
b1011110 G
b1011110 I
1!
#985000
0!
#990000
b1011111 I
b1011111 G
b1011111 E
b0 6
1!
#995000
0!
#1000000
1"
02
b1100000 E
b1100000 G
b1100000 I
1!
#1005000
0!
#1010000
b1100001 I
b1100001 G
b1100001 E
0<
b1 5
1!
#1015000
0!
#1020000
b11 5
b1100010 E
b1100010 G
b1100010 I
1!
#1025000
0!
#1030000
b1100011 I
b1100011 G
b1100011 E
b111 5
1!
#1035000
0!
#1040000
b1111 5
b1100100 E
b1100100 G
b1100100 I
1!
#1045000
0!
#1050000
b1100101 I
b1100101 G
b1100101 E
b11111 5
1!
#1055000
0!
#1060000
b111111 5
b1100110 E
b1100110 G
b1100110 I
1!
#1065000
0!
#1070000
b1100111 I
b1100111 G
b1100111 E
b1111111 5
1!
#1075000
0!
#1080000
b11111111 5
b1101000 E
b1101000 G
b1101000 I
1!
#1085000
0!
#1090000
1#
b1101001 I
b1101001 G
b1101001 E
13
1!
#1095000
0!
#1100000
b1 6
b101 4
b101 =
b101 D
1;
b1101010 E
b1101010 G
b1101010 I
1!
#1105000
0!
#1110000
b1101011 I
b1101011 G
b1101011 E
b11 6
1!
#1115000
0!
#1120000
b111 6
b1101100 E
b1101100 G
b1101100 I
1!
#1125000
0!
#1130000
b1101101 I
b1101101 G
b1101101 E
b1111 6
1!
#1135000
0!
#1140000
b11111 6
b1101110 E
b1101110 G
b1101110 I
1!
#1145000
0!
#1150000
b1101111 I
b1101111 G
b1101111 E
b111111 6
1!
#1155000
0!
#1160000
b1111111 6
b1110000 E
b1110000 G
b1110000 I
1!
#1165000
0!
#1170000
b1110001 I
b1110001 G
b1110001 E
b11111111 6
1!
#1175000
0!
#1180000
12
b1110010 E
b1110010 G
b1110010 I
1!
#1185000
0!
#1190000
0"
b1110011 I
b1110011 G
b1110011 E
1<
1!
#1195000
0!
#1200000
b11111110 5
b1110100 E
b1110100 G
b1110100 I
1!
#1205000
0!
#1210000
1"
b1110101 I
b1110101 G
b1110101 E
b11111100 5
1!
#1215000
0!
#1220000
0"
b11111001 5
b1110110 E
b1110110 G
b1110110 I
1!
#1225000
0!
#1230000
b1110111 I
b1110111 G
b1110111 E
b11110010 5
1!
#1235000
0!
#1240000
b11100100 5
b1111000 E
b1111000 G
b1111000 I
1!
#1245000
0!
#1250000
b1111001 I
b1111001 G
b1111001 E
b11001000 5
1!
#1255000
0!
#1260000
b10010000 5
b1111010 E
b1111010 G
b1111010 I
1!
#1265000
0!
#1270000
b1111011 I
b1111011 G
b1111011 E
b100000 5
1!
#1275000
0!
#1280000
b1000000 5
b1111100 E
b1111100 G
b1111100 I
1!
#1285000
0!
#1290000
b1111101 I
b1111101 G
b1111101 E
b10000000 5
1!
#1295000
0!
#1300000
b0 5
b1111110 E
b1111110 G
b1111110 I
1!
#1305000
0!
#1310000
0#
b1111111 I
b1111111 G
b1111111 E
03
1!
#1315000
0!
#1320000
b11111110 6
b110 4
b110 =
b110 D
0;
b10000000 E
b10000000 G
b10000000 I
1!
#1325000
0!
#1330000
b10000001 I
b10000001 G
b10000001 E
b11111100 6
1!
#1335000
0!
#1340000
b11111000 6
b10000010 E
b10000010 G
b10000010 I
1!
#1345000
0!
#1350000
b10000011 I
b10000011 G
b10000011 E
b11110000 6
1!
#1355000
0!
#1360000
b11100000 6
b10000100 E
b10000100 G
b10000100 I
1!
#1365000
0!
#1370000
b10000101 I
b10000101 G
b10000101 E
b11000000 6
1!
#1375000
0!
#1380000
b10000000 6
b10000110 E
b10000110 G
b10000110 I
1!
#1385000
0!
#1390000
1"
b10000111 I
b10000111 G
b10000111 E
b0 6
1!
#1395000
0!
#1400000
b1 5
02
b10001000 E
b10001000 G
b10001000 I
1!
#1405000
0!
#1410000
b10001001 I
b10001001 G
b10001001 E
0<
b11 5
1!
#1415000
0!
#1420000
b111 5
b10001010 E
b10001010 G
b10001010 I
1!
#1425000
0!
#1430000
b10001011 I
b10001011 G
b10001011 E
b1111 5
1!
#1435000
0!
#1440000
b11111 5
b10001100 E
b10001100 G
b10001100 I
1!
#1445000
0!
#1450000
b10001101 I
b10001101 G
b10001101 E
b111111 5
1!
#1455000
0!
#1460000
b1111111 5
b10001110 E
b10001110 G
b10001110 I
1!
#1465000
0!
#1470000
b10001111 I
b10001111 G
b10001111 E
b11111111 5
1!
#1475000
0!
#1480000
13
b10010000 E
b10010000 G
b10010000 I
1!
#1485000
0!
#1490000
1#
b10010001 I
b10010001 G
b10010001 E
b111 4
b111 =
b111 D
1;
1!
#1495000
0!
#1500000
b1 6
b10010010 E
b10010010 G
b10010010 I
1!
#1505000
0!
#1510000
0#
b10010011 I
b10010011 G
b10010011 E
b11 6
1!
#1515000
0!
#1520000
1#
b110 6
b10010100 E
b10010100 G
b10010100 I
1!
#1525000
0!
#1530000
b10010101 I
b10010101 G
b10010101 E
b1101 6
1!
#1535000
0!
#1540000
b11011 6
b10010110 E
b10010110 G
b10010110 I
1!
#1545000
0!
#1550000
b10010111 I
b10010111 G
b10010111 E
b110111 6
1!
#1555000
0!
#1560000
b1101111 6
b10011000 E
b10011000 G
b10011000 I
1!
#1565000
0!
#1570000
b10011001 I
b10011001 G
b10011001 E
b11011111 6
1!
#1575000
0!
#1580000
b10111111 6
b10011010 E
b10011010 G
b10011010 I
1!
#1585000
0!
#1590000
0"
b10011011 I
b10011011 G
b10011011 E
b1111111 6
1!
#1595000
0!
#1600000
b11111110 5
b11111111 6
b10011100 E
b10011100 G
b10011100 I
1!
#1605000
0!
#1610000
1"
b10011101 I
b10011101 G
b10011101 E
12
b11111100 5
1!
#1615000
0!
#1620000
0"
b11111001 5
1<
b10011110 E
b10011110 G
b10011110 I
1!
#1625000
0!
#1630000
b10011111 I
b10011111 G
b10011111 E
b11110010 5
1!
#1635000
0!
#1640000
b11100100 5
b10100000 E
b10100000 G
b10100000 I
1!
#1645000
0!
#1650000
b10100001 I
b10100001 G
b10100001 E
b11001000 5
1!
#1655000
0!
#1660000
b10010000 5
b10100010 E
b10100010 G
b10100010 I
1!
#1665000
0!
#1670000
b10100011 I
b10100011 G
b10100011 E
b100000 5
1!
#1675000
0!
#1680000
b1000000 5
b10100100 E
b10100100 G
b10100100 I
1!
#1685000
0!
#1690000
0#
b10100101 I
b10100101 G
b10100101 E
b10000000 5
1!
#1695000
0!
#1700000
b0 5
b11111110 6
b10100110 E
b10100110 G
b10100110 I
1!
#1705000
0!
#1710000
b10100111 I
b10100111 G
b10100111 E
b11111100 6
03
1!
#1715000
0!
#1720000
b11111000 6
b1000 4
b1000 =
b1000 D
0;
b10101000 E
b10101000 G
b10101000 I
1!
#1725000
0!
#1730000
b10101001 I
b10101001 G
b10101001 E
b11110000 6
1!
#1735000
0!
#1740000
b11100000 6
b10101010 E
b10101010 G
b10101010 I
1!
#1745000
0!
#1750000
b10101011 I
b10101011 G
b10101011 E
b11000000 6
1!
#1755000
0!
#1760000
b10000000 6
b10101100 E
b10101100 G
b10101100 I
1!
#1765000
0!
#1770000
b10101101 I
b10101101 G
b10101101 E
b0 6
1!
#1775000
0!
#1780000
02
b10101110 E
b10101110 G
b10101110 I
1!
#1785000
0!
#1790000
1"
b10101111 I
b10101111 G
b10101111 E
0<
1!
#1795000
0!
#1800000
b1 5
b10110000 E
b10110000 G
b10110000 I
1!
#1805000
0!
#1810000
0"
b10110001 I
b10110001 G
b10110001 E
b11 5
1!
#1815000
0!
#1820000
1"
b110 5
b10110010 E
b10110010 G
b10110010 I
1!
#1825000
0!
#1830000
b10110011 I
b10110011 G
b10110011 E
b1101 5
1!
#1835000
0!
#1840000
b11011 5
b10110100 E
b10110100 G
b10110100 I
1!
#1845000
0!
#1850000
b10110101 I
b10110101 G
b10110101 E
b110111 5
1!
#1855000
0!
#1860000
b1101111 5
b10110110 E
b10110110 G
b10110110 I
1!
#1865000
0!
#1870000
b10110111 I
b10110111 G
b10110111 E
b11011111 5
1!
#1875000
0!
#1880000
b10111111 5
b10111000 E
b10111000 G
b10111000 I
1!
#1885000
0!
#1890000
b10111001 I
b10111001 G
b10111001 E
b1111111 5
1!
#1895000
0!
#1900000
1#
b11111111 5
b10111010 E
b10111010 G
b10111010 I
1!
#1905000
0!
#1910000
b10111011 I
b10111011 G
b10111011 E
b1 6
13
1!
#1915000
0!
#1920000
b11 6
b1001 4
b1001 =
b1001 D
1;
b10111100 E
b10111100 G
b10111100 I
1!
#1925000
0!
#1930000
b10111101 I
b10111101 G
b10111101 E
b111 6
1!
#1935000
0!
#1940000
b1111 6
b10111110 E
b10111110 G
b10111110 I
1!
#1945000
0!
#1950000
b10111111 I
b10111111 G
b10111111 E
b11111 6
1!
#1955000
0!
#1960000
b111111 6
b11000000 E
b11000000 G
b11000000 I
1!
#1965000
0!
#1970000
b11000001 I
b11000001 G
b11000001 E
b1111111 6
1!
#1975000
0!
#1980000
b11111111 6
b11000010 E
b11000010 G
b11000010 I
1!
#1985000
0!
#1990000
0"
b11000011 I
b11000011 G
b11000011 E
12
1!
#1995000
0!
#2000000
b11111110 5
1<
b11000100 E
b11000100 G
b11000100 I
1!
#2005000
0!
#2010000
b11000101 I
b11000101 G
b11000101 E
b11111100 5
1!
#2015000
0!
#2020000
b11111000 5
b11000110 E
b11000110 G
b11000110 I
1!
#2025000
0!
#2030000
b11000111 I
b11000111 G
b11000111 E
b11110000 5
1!
#2035000
0!
#2040000
b11100000 5
b11001000 E
b11001000 G
b11001000 I
1!
#2045000
0!
#2050000
b11001001 I
b11001001 G
b11001001 E
b11000000 5
1!
#2055000
0!
#2060000
b10000000 5
b11001010 E
b11001010 G
b11001010 I
1!
#2065000
0!
#2070000
b11001011 I
b11001011 G
b11001011 E
b0 5
1!
#2075000
0!
#2080000
03
b11001100 E
b11001100 G
b11001100 I
1!
#2085000
0!
#2090000
0#
b11001101 I
b11001101 G
b11001101 E
b1010 4
b1010 =
b1010 D
0;
1!
#2095000
0!
#2100000
b11111110 6
b11001110 E
b11001110 G
b11001110 I
1!
#2105000
0!
#2110000
1#
b11001111 I
b11001111 G
b11001111 E
b11111100 6
1!
#2115000
0!
#2120000
0#
b11111001 6
b11010000 E
b11010000 G
b11010000 I
1!
#2125000
0!
#2130000
b11010001 I
b11010001 G
b11010001 E
b11110010 6
1!
#2135000
0!
#2140000
b11100100 6
b11010010 E
b11010010 G
b11010010 I
1!
#2145000
0!
#2150000
b11010011 I
b11010011 G
b11010011 E
b11001000 6
1!
#2155000
0!
#2160000
b10010000 6
b11010100 E
b11010100 G
b11010100 I
1!
#2165000
0!
#2170000
b11010101 I
b11010101 G
b11010101 E
b100000 6
1!
#2175000
0!
#2180000
b1000000 6
b11010110 E
b11010110 G
b11010110 I
1!
#2185000
0!
#2190000
b11010111 I
b11010111 G
b11010111 E
b10000000 6
1!
#2195000
0!
#2200000
1"
b0 6
b11011000 E
b11011000 G
b11011000 I
1!
#2205000
0!
#2210000
b11011001 I
b11011001 G
b11011001 E
02
b1 5
1!
#2215000
0!
#2220000
b11 5
0<
b11011010 E
b11011010 G
b11011010 I
1!
#2225000
0!
#2230000
b11011011 I
b11011011 G
b11011011 E
b111 5
1!
#2235000
0!
#2240000
b1111 5
b11011100 E
b11011100 G
b11011100 I
1!
#2245000
0!
#2250000
b11011101 I
b11011101 G
b11011101 E
b11111 5
1!
#2255000
0!
#2260000
b111111 5
b11011110 E
b11011110 G
b11011110 I
1!
#2265000
0!
#2270000
b11011111 I
b11011111 G
b11011111 E
b1111111 5
1!
#2275000
0!
#2280000
b11111111 5
b11100000 E
b11100000 G
b11100000 I
1!
#2285000
0!
#2290000
1#
b11100001 I
b11100001 G
b11100001 E
13
1!
#2295000
0!
#2300000
b1 6
b1011 4
b1011 =
b1011 D
1;
b11100010 E
b11100010 G
b11100010 I
1!
#2305000
0!
#2310000
b11100011 I
b11100011 G
b11100011 E
b11 6
1!
#2315000
0!
#2320000
b111 6
b11100100 E
b11100100 G
b11100100 I
1!
#2325000
0!
#2330000
b11100101 I
b11100101 G
b11100101 E
b1111 6
1!
#2335000
0!
#2340000
b11111 6
b11100110 E
b11100110 G
b11100110 I
1!
#2345000
0!
#2350000
b11100111 I
b11100111 G
b11100111 E
b111111 6
1!
#2355000
0!
#2360000
b1111111 6
b11101000 E
b11101000 G
b11101000 I
1!
#2365000
0!
#2370000
b11101001 I
b11101001 G
b11101001 E
b11111111 6
1!
#2375000
0!
#2380000
12
b11101010 E
b11101010 G
b11101010 I
1!
#2385000
0!
#2390000
0"
b11101011 I
b11101011 G
b11101011 E
1<
1!
#2395000
0!
#2400000
b11111110 5
b11101100 E
b11101100 G
b11101100 I
1!
#2405000
0!
#2410000
b11101101 I
b11101101 G
b11101101 E
b11111100 5
1!
#2415000
0!
#2420000
b11111000 5
b11101110 E
b11101110 G
b11101110 I
1!
#2425000
0!
#2430000
b11101111 I
b11101111 G
b11101111 E
b11110000 5
1!
#2435000
0!
#2440000
b11100000 5
b11110000 E
b11110000 G
b11110000 I
1!
#2445000
0!
#2450000
b11110001 I
b11110001 G
b11110001 E
b11000000 5
1!
#2455000
0!
#2460000
b10000000 5
b11110010 E
b11110010 G
b11110010 I
1!
#2465000
0!
#2470000
b11110011 I
b11110011 G
b11110011 E
b0 5
1!
#2475000
0!
#2480000
03
b11110100 E
b11110100 G
b11110100 I
1!
#2485000
0!
#2490000
b11110101 I
b11110101 G
b11110101 E
b1100 4
b1100 =
b1100 D
0;
1!
#2495000
0!
#2500000
0#
b11110110 E
b11110110 G
b11110110 I
1!
#2505000
0!
#2510000
b11110111 I
b11110111 G
b11110111 E
b11111110 6
1!
#2515000
0!
#2520000
b11111100 6
b11111000 E
b11111000 G
b11111000 I
1!
#2525000
0!
#2530000
b11111001 I
b11111001 G
b11111001 E
b11111000 6
1!
#2535000
0!
#2540000
b11110000 6
b11111010 E
b11111010 G
b11111010 I
1!
#2545000
0!
#2550000
b11111011 I
b11111011 G
b11111011 E
b11100000 6
1!
#2555000
0!
#2560000
b11000000 6
b11111100 E
b11111100 G
b11111100 I
1!
#2565000
0!
#2570000
b11111101 I
b11111101 G
b11111101 E
b10000000 6
1!
#2575000
0!
#2580000
b0 6
b11111110 E
b11111110 G
b11111110 I
1!
#2585000
0!
#2590000
1"
b11111111 I
b11111111 G
b11111111 E
02
1!
#2595000
0!
#2600000
0"
b1 5
0<
1+
b0 E
b0 G
b0 I
1!
#2605000
0!
#2610000
1"
b1 I
b1 G
b1 E
b10 5
1!
#2615000
0!
#2620000
b101 5
b10 E
b10 G
b10 I
1!
#2625000
0!
#2630000
b11 I
b11 G
b11 E
b1011 5
1!
#2635000
0!
#2640000
b10111 5
b100 E
b100 G
b100 I
1!
#2645000
0!
#2650000
b101 I
b101 G
b101 E
b101111 5
1!
#2655000
0!
#2660000
b1011111 5
b110 E
b110 G
b110 I
1!
#2665000
0!
#2670000
b111 I
b111 G
b111 E
b10111111 5
1!
#2675000
0!
#2680000
b1111111 5
b1000 E
b1000 G
b1000 I
1!
#2685000
0!
#2690000
b1001 I
b1001 G
b1001 E
b11111111 5
1!
#2695000
0!
#2700000
1#
13
b1010 E
b1010 G
b1010 I
1!
#2705000
0!
#2710000
0#
b1011 I
b1011 G
b1011 E
b1101 4
b1101 =
b1101 D
1;
b1 6
1!
#2715000
0!
#2720000
1#
b10 6
b1100 E
b1100 G
b1100 I
1!
#2725000
0!
#2730000
b1101 I
b1101 G
0+
b1101 E
b101 6
1!
#2735000
0!
#2740000
b1011 6
b1110 E
b1110 G
b1110 I
1!
#2745000
0!
